{
  "parent": "mffs:projector",
  "criteria": {
    "create_field_shape": {
      "trigger": "mffs:field_shape"
    }
  },
  "display": {
    "description": {
      "translate": "advancements.mffs.field_shape.description"
    },
    "frame": "goal",
    "icon": {
      "count": 1,
      "id": "mffs:custom_mode"
    },
    "title": {
      "translate": "advancements.mffs.field_shape.title"
    }
  },
  "requirements": [
    [
      "create_field_shape"
    ]
  ],
  "sends_telemetry_event": true
}